deployhub/__init__.py
deployhub/dhapi.py
deployhub-9.3.210.data/scripts/dh
deployhub-9.3.210.data/scripts/helminfo.sh
deployhub-9.3.210.dist-info/LICENSE
deployhub-9.3.210.dist-info/METADATA
deployhub-9.3.210.dist-info/WHEEL
deployhub-9.3.210.dist-info/top_level.txt
deployhub-9.3.210.dist-info/RECORD
