Metadata-Version: 2.1
Name: deployhub
Version: 9.3.210
Home-page: https://ortelius.io
Author: Steve Taylor
Author-email: steve@deployhub.com
License: GNU AFFERO GENERAL PUBLIC LICENSE
Project-URL: Project Repo, https://github.com/ortelius/compupdate
Project-URL: Issues, https://github.com/ortelius/ortelius/issues
Project-URL: CLI Documentation, https://github.com/ortelius/compupdate/blob/main/doc/dh.md
Project-URL: Python API Documentation, https://github.com/ortelius/compupdate/blob/main/doc/deployhub.md
Project-URL: Jenkinsfile Example, https://github.com/ortelius/compupdate/blob/main/Jenkinsfile
Requires-Python: >=3.6
License-File: LICENSE
Requires-Dist: click
Requires-Dist: qtoml
Requires-Dist: PyYAML
Requires-Dist: requests
Requires-Dist: configobj
Requires-Dist: flatten-dict
Requires-Dist: pydantic
Requires-Dist: certifi
